LICENSE
MANIFEST.in
README.md
requirements.txt
setup.py
bin/fate
fate/__init__.py
fate/fate.py
fate/helpers.py
fate.egg-info/PKG-INFO
fate.egg-info/SOURCES.txt
fate.egg-info/dependency_links.txt
fate.egg-info/requires.txt
fate.egg-info/top_level.txt